machy/__init__.py
machy/index.py
machy-1.0.1.dist-info/METADATA
machy-1.0.1.dist-info/WHEEL
machy-1.0.1.dist-info/top_level.txt
machy-1.0.1.dist-info/RECORD
