Metadata-Version: 2.1
Name: machy
Version: 1.0.1
Summary: Web scraper utils
Home-page: https://github.com/Ennoriel/machy
Author: Maxime Dupont
License: MIT
